ean_tools/__init__.py
ean_tools/barcode_info.py
ean_tools/barcode_prefixes.py
ean_tools/check_digits.py
ean_tools/data/gs1-8-prefixes.yaml
ean_tools/data/gs1-prefixes.yaml
ean_tools/data/isbn-prefixes.yaml
ean_tools/normalization.py
ean_tools-0.1.1.dist-info/METADATA
ean_tools-0.1.1.dist-info/WHEEL
ean_tools-0.1.1.dist-info/RECORD
