Metadata-Version: 2.3
Name: ean-tools
Version: 0.1.1
Summary: Collection of tools for validating and getting information about EAN (UPC, GTIN) and ISBN barcodes.
Home-page: https://github.com/ean-db/ean-tools
License: MIT
Keywords: barcode,ean,upc,isbn,gtin
Author: EAN-DB
Author-email: support@ean-db.com
Requires-Python: >=3.12
Classifier: License :: OSI Approved :: MIT License
Classifier: Programming Language :: Python :: 3
Classifier: Programming Language :: Python :: 3.12
Classifier: Programming Language :: Python :: 3.13
Classifier: Topic :: Software Development :: Libraries :: Python Modules
Requires-Dist: PyYaml (>=6)
Requires-Dist: affix-tree (>=0.1.1)
Project-URL: Repository, https://github.com/ean-db/ean-tools
